{
  "source_binding_set_id": "bindings-2026-06-28-playable-ruin-library-v1",
  "bindings": [
    {
      "id": "binding-hero-memory-prism-catalogue",
      "artifact_id": "hero-memory-prism-catalogue",
      "source_type": "article",
      "source_url": "https://www.creativebloq.com/3d/video-game-design/get-inspired-by-the-best-indie-game-devs",
      "window_type": "web",
      "hover_behavior": "preview",
      "click_behavior": "pin-open",
      "playback_persistence": true,
      "fallback_type": "rich-preview",
      "title": "Get inspired by 19 of the most interesting indie game devs",
      "kicker": "creativebloq.com",
      "excerpt": "Discover the creators pushing boundaries with bold ideas, stunning art, and unforgettable gameplay.",
      "source_title": "Get inspired by 19 of the most interesting indie game devs",
      "source_summary": "Discover the creators pushing boundaries with bold ideas, stunning art, and unforgettable gameplay.",
      "source_domain": "creativebloq.com",
      "source_meta": "Get inspired by 19 of the most interesting indie game devs",
      "source_image_url": "https://cdn.mos.cms.futurecdn.net/od95GWYNMnxW2uW4LQtqoV-1920-80.jpg",
      "source_image_alt": "Get inspired by 19 of the most interesting indie game devs preview image",
      "source_visual": {
        "poster_asset_path": "/editions/2026-06-28-playable-ruin-library-v1/assets/source-posters/binding-hero-memory-prism-catalogue.jpg",
        "render_mode": "poster-crop",
        "crop_risk": "low",
        "focal_point": {
          "x": 0.581,
          "y": 0.5736
        },
        "poster_crop": {
          "x": 0.0,
          "y": 0.0,
          "width": 1.0,
          "height": 1.0
        },
        "image_width": 1920,
        "image_height": 1080,
        "analysis": {
          "method": "supervision-contour-union",
          "supervision_version": "0.28.0",
          "edge_density": 0.01234,
          "candidate_box_count": 24
        }
      }
    },
    {
      "id": "binding-hero-hero-epic-crop-stone-relief",
      "artifact_id": "hero-hero-epic-crop-stone-relief",
      "source_type": "article",
      "source_url": "https://www.creativeuncut.com/thumbs/hp/hp-er.jpg",
      "window_type": "web",
      "hover_behavior": "preview",
      "click_behavior": "pin-open",
      "playback_persistence": true,
      "fallback_type": "rich-preview",
      "title": "Elden Ring Art",
      "kicker": "creativeuncut.com",
      "excerpt": "Image found on a page derived from the anchor research.",
      "source_title": "Elden Ring Art",
      "source_summary": "Image found on a page derived from the anchor research.",
      "source_domain": "creativeuncut.com",
      "source_meta": "Elden Ring Art",
      "source_image_url": "https://www.creativeuncut.com/thumbs/hp/hp-er.jpg",
      "source_image_alt": "Elden Ring Art preview image",
      "source_visual": {
        "poster_asset_path": "/editions/2026-06-28-playable-ruin-library-v1/assets/source-posters/binding-hero-hero-epic-crop-stone-relief.jpg",
        "render_mode": "poster-crop",
        "crop_risk": "low",
        "focal_point": {
          "x": 0.5109,
          "y": 0.5
        },
        "poster_crop": {
          "x": 0.1531,
          "y": 0.0,
          "width": 0.6937,
          "height": 1.0
        },
        "image_width": 640,
        "image_height": 250,
        "analysis": {
          "method": "supervision-contour-union",
          "supervision_version": "0.28.0",
          "edge_density": 0.13026,
          "candidate_box_count": 24
        }
      }
    },
    {
      "id": "binding-module-inventory-plaque-for-indie-styles",
      "artifact_id": "module-inventory-plaque-for-indie-styles",
      "source_type": "article",
      "source_url": "https://www.creativeuncut.com/thumbs/hp/hp-owf.jpg",
      "window_type": "web",
      "hover_behavior": "preview",
      "click_behavior": "pin-open",
      "playback_persistence": true,
      "fallback_type": "rich-preview",
      "title": "Overwatch Art",
      "kicker": "creativeuncut.com",
      "excerpt": "Image found on a page derived from the anchor research.",
      "source_title": "Overwatch Art",
      "source_summary": "Image found on a page derived from the anchor research.",
      "source_domain": "creativeuncut.com",
      "source_meta": "Overwatch Art",
      "source_image_url": "https://www.creativeuncut.com/thumbs/hp/hp-owf.jpg",
      "source_image_alt": "Overwatch Art preview image",
      "source_visual": {
        "poster_asset_path": "/editions/2026-06-28-playable-ruin-library-v1/assets/source-posters/binding-module-inventory-plaque-for-indie-styles.jpg",
        "render_mode": "poster-crop",
        "crop_risk": "low",
        "focal_point": {
          "x": 0.5953,
          "y": 0.5
        },
        "poster_crop": {
          "x": 0.1844,
          "y": 0.0,
          "width": 0.6937,
          "height": 1.0
        },
        "image_width": 640,
        "image_height": 250,
        "analysis": {
          "method": "supervision-contour-union",
          "supervision_version": "0.28.0",
          "edge_density": 0.09611,
          "candidate_box_count": 24
        }
      }
    },
    {
      "id": "binding-module-portfolio-slit-procession",
      "artifact_id": "module-portfolio-slit-procession",
      "source_type": "article",
      "source_url": "https://www.creativeuncut.com/thumbs/hp/hp-de.jpg",
      "window_type": "web",
      "hover_behavior": "preview",
      "click_behavior": "pin-open",
      "playback_persistence": true,
      "fallback_type": "rich-preview",
      "title": "Disco Elysium Art",
      "kicker": "creativeuncut.com",
      "excerpt": "Image found on a page derived from the anchor research.",
      "source_title": "Disco Elysium Art",
      "source_summary": "Image found on a page derived from the anchor research.",
      "source_domain": "creativeuncut.com",
      "source_meta": "Disco Elysium Art",
      "source_image_url": "https://www.creativeuncut.com/thumbs/hp/hp-de.jpg",
      "source_image_alt": "Disco Elysium Art preview image",
      "source_visual": {
        "poster_asset_path": "/editions/2026-06-28-playable-ruin-library-v1/assets/source-posters/binding-module-portfolio-slit-procession.jpg",
        "render_mode": "poster-crop",
        "crop_risk": "low",
        "focal_point": {
          "x": 0.5016,
          "y": 0.5
        },
        "poster_crop": {
          "x": 0.1531,
          "y": 0.0,
          "width": 0.6937,
          "height": 1.0
        },
        "image_width": 640,
        "image_height": 250,
        "analysis": {
          "method": "supervision-contour-union",
          "supervision_version": "0.28.0",
          "edge_density": 0.06781,
          "candidate_box_count": 24
        }
      }
    },
    {
      "id": "binding-module-commercial-preview-shard",
      "artifact_id": "module-commercial-preview-shard",
      "source_type": "article",
      "source_url": "https://pixune.com/blog/indie-game-art-styles/",
      "window_type": "web",
      "hover_behavior": "preview",
      "click_behavior": "pin-open",
      "playback_persistence": true,
      "fallback_type": "rich-preview",
      "title": "Explore Popular Indie Game Art Styles and Aesthetics",
      "kicker": "pixune.com",
      "excerpt": "Explore the most popular indie game art styles, their characteristics, and how aesthetics shape gameplay, marketing, and player experience.",
      "source_title": "Explore Popular Indie Game Art Styles and Aesthetics",
      "source_summary": "Explore the most popular indie game art styles, their characteristics, and how aesthetics shape gameplay, marketing, and player experience.",
      "source_domain": "pixune.com",
      "source_meta": "Explore Popular Indie Game Art Styles and Aesthetics",
      "source_image_url": "https://pixune.com/wp-content/uploads/2024/09/screen-shot-2015-02-25-at-11-51-32-am-1.webp",
      "source_image_alt": "Explore Popular Indie Game Art Styles and Aesthetics preview image",
      "source_visual": {
        "poster_asset_path": "/editions/2026-06-28-playable-ruin-library-v1/assets/source-posters/binding-module-commercial-preview-shard.jpg",
        "render_mode": "poster-crop",
        "crop_risk": "low",
        "focal_point": {
          "x": 0.502,
          "y": 0.5071
        },
        "poster_crop": {
          "x": 0.0392,
          "y": 0.0,
          "width": 0.9215,
          "height": 1.0
        },
        "image_width": 1504,
        "image_height": 780,
        "analysis": {
          "method": "supervision-contour-union",
          "supervision_version": "0.28.0",
          "edge_density": 0.02538,
          "candidate_box_count": 24
        }
      }
    },
    {
      "id": "binding-module-secondary-source-anchor",
      "artifact_id": "module-secondary-source-anchor",
      "source_type": "article",
      "source_url": "https://www.sitebuilderreport.com/inspiration/game-developer-portfolios",
      "window_type": "web",
      "hover_behavior": "preview",
      "click_behavior": "pin-open",
      "playback_persistence": true,
      "fallback_type": "rich-preview",
      "title": "Game Developer Portfolios: 15+ Well-Designed Examples (2026)",
      "kicker": "sitebuilderreport.com",
      "excerpt": "A collection of inspiring game developer portfolio websites created with top website builders like Squarespace, Wix, WordPress, and Webflow.",
      "source_title": "Game Developer Portfolios: 15+ Well-Designed Examples (2026)",
      "source_summary": "A collection of inspiring game developer portfolio websites created with top website builders like Squarespace, Wix, WordPress, and Webflow.",
      "source_domain": "sitebuilderreport.com",
      "source_meta": "Game Developer Portfolios: 15+ Well-Designed Examples (2026)",
      "source_image_url": "https://ucarecdn.com/1a44062d-0fb8-4df2-aa13-714e6a1beeab/",
      "source_image_alt": "Game Developer Portfolios: 15+ Well-Designed Examples (2026) preview image",
      "source_visual": {
        "poster_asset_path": "/editions/2026-06-28-playable-ruin-library-v1/assets/source-posters/binding-module-secondary-source-anchor.jpg",
        "render_mode": "poster-crop",
        "crop_risk": "low",
        "focal_point": {
          "x": 0.5,
          "y": 0.5289
        },
        "poster_crop": {
          "x": 0.0,
          "y": 0.0408,
          "width": 1.0,
          "height": 0.9176
        },
        "image_width": 1920,
        "image_height": 1177,
        "analysis": {
          "method": "supervision-contour-union",
          "supervision_version": "0.28.0",
          "edge_density": 0.12085,
          "candidate_box_count": 24
        }
      }
    },
    {
      "id": "binding-module-commercial-preview-shard-2",
      "artifact_id": "module-commercial-preview-shard-2",
      "source_type": "tweet",
      "source_url": "https://x.com/adilinthewild/status/2070561738433712369",
      "window_type": "social",
      "hover_behavior": "preview",
      "click_behavior": "pin-open",
      "playback_persistence": true,
      "fallback_type": "rich-preview",
      "title": "@adilinthewild: Adil here from @higgsfield_ai 🫡 first tweet ever so i'm not wasting it made...",
      "kicker": "x.com",
      "excerpt": "Adil here from @higgsfield_ai 🫡 first tweet ever so i'm not wasting it made this commercial with AI - here's every prompt, every skill all of it",
      "source_title": "@adilinthewild: Adil here from @higgsfield_ai 🫡 first tweet ever so i'm not wasting it made...",
      "source_summary": "Adil here from @higgsfield_ai 🫡 first tweet ever so i'm not wasting it made this commercial with AI - here's every prompt, every skill all of it",
      "source_domain": "x.com",
      "source_meta": "@adilinthewild: Adil here from @higgsfield_ai 🫡 first tweet ever so i'm not wasting it made this...",
      "source_image_url": "https://pbs.twimg.com/amplify_video_thumb/2070561638391152640/img/3vDpx36Z3sZYHblJ.jpg",
      "source_image_alt": "@adilinthewild: Adil here from @higgsfield_ai 🫡 first tweet ever so i'm not wasting it made... preview image",
      "source_visual": {
        "poster_asset_path": "/editions/2026-06-28-playable-ruin-library-v1/assets/source-posters/binding-module-commercial-preview-shard-2.jpg",
        "render_mode": "poster-crop",
        "crop_risk": "low",
        "focal_point": {
          "x": 0.5,
          "y": 0.5089
        },
        "poster_crop": {
          "x": 0.0,
          "y": 0.0,
          "width": 1.0,
          "height": 1.0
        },
        "image_width": 1200,
        "image_height": 675,
        "analysis": {
          "method": "supervision-contour-union",
          "supervision_version": "0.28.0",
          "edge_density": 0.03453,
          "candidate_box_count": 24
        }
      }
    },
    {
      "id": "binding-module-security-checklist-notch",
      "artifact_id": "module-security-checklist-notch",
      "source_type": "tweet",
      "source_url": "https://x.com/PrajwalTomar_/status/2070153296862728515",
      "window_type": "social",
      "hover_behavior": "preview",
      "click_behavior": "pin-open",
      "playback_persistence": true,
      "fallback_type": "rich-preview",
      "title": "@PrajwalTomar_: Vibe coders are getting sued. People are shipping apps with real users and...",
      "kicker": "x.com",
      "excerpt": "Vibe coders are getting sued. People are shipping apps with real users and skipping the boring stuff that kills them. A 20+ year dev shared the pre-launch checklist every AI builder needs. I added what I learned after shipping 60+ apps at the agency. Don't skip this: 1. Protect yourself, not just your app. The moment you collect user data you're in legal...",
      "source_title": "@PrajwalTomar_: Vibe coders are getting sued. People are shipping apps with real users and...",
      "source_summary": "Vibe coders are getting sued. People are shipping apps with real users and skipping the boring stuff that kills them. A 20+ year dev shared the pre-launch checklist every AI builder needs. I added what I learned after shipping 60+ apps at the agency. Don't skip this: 1. Protect yourself, not just your app. The moment you collect user data you're in legal territory (GDPR, CCPA). Have a privacy policy. Know where user data lives. 2. Row Level Security. Without RLS, anyone can open DevTools and read your entire...",
      "source_domain": "x.com",
      "source_meta": "@PrajwalTomar_: Vibe coders are getting sued. People are shipping apps with real users and skipp...",
      "source_image_url": "https://pbs.twimg.com/media/HLqpc7ZaAAAaVVY.jpg?name=orig",
      "source_image_alt": "@PrajwalTomar_: Vibe coders are getting sued. People are shipping apps with real users and... preview image",
      "source_visual": {
        "poster_asset_path": "/editions/2026-06-28-playable-ruin-library-v1/assets/source-posters/binding-module-security-checklist-notch.jpg",
        "render_mode": "poster-crop",
        "crop_risk": "medium",
        "focal_point": {
          "x": 0.4625,
          "y": 0.506
        },
        "poster_crop": {
          "x": 0.0,
          "y": 0.1883,
          "width": 1.0,
          "height": 0.6234
        },
        "image_width": 1572,
        "image_height": 1418,
        "analysis": {
          "method": "supervision-contour-union",
          "supervision_version": "0.28.0",
          "edge_density": 0.05749,
          "candidate_box_count": 19
        }
      }
    },
    {
      "id": "binding-module-secondary-source-anchor-2",
      "artifact_id": "module-secondary-source-anchor-2",
      "source_type": "tweet",
      "source_url": "https://x.com/ApoStructura/status/2070238964452089858",
      "window_type": "social",
      "hover_behavior": "preview",
      "click_behavior": "pin-open",
      "playback_persistence": true,
      "fallback_type": "rich-preview",
      "title": "@ApoStructura: Putting AI water use in context",
      "kicker": "x.com",
      "excerpt": "Putting AI water use in context",
      "source_title": "@ApoStructura: Putting AI water use in context",
      "source_summary": "Putting AI water use in context",
      "source_domain": "x.com",
      "source_meta": "@ApoStructura: Putting AI water use in context",
      "source_image_url": "https://pbs.twimg.com/amplify_video_thumb/2070238874345881600/img/cvASXzEEENJNoRu-.jpg",
      "source_image_alt": "@ApoStructura: Putting AI water use in context preview image",
      "source_visual": {
        "poster_asset_path": "/editions/2026-06-28-playable-ruin-library-v1/assets/source-posters/binding-module-secondary-source-anchor-2.jpg",
        "render_mode": "poster-crop",
        "crop_risk": "medium",
        "focal_point": {
          "x": 0.3046,
          "y": 0.5519
        },
        "poster_crop": {
          "x": 0.0,
          "y": 0.2185,
          "width": 1.0,
          "height": 0.562
        },
        "image_width": 1080,
        "image_height": 1080,
        "analysis": {
          "method": "supervision-contour-union",
          "supervision_version": "0.28.0",
          "edge_density": 0.01272,
          "candidate_box_count": 4
        }
      }
    }
  ]
}
