{
  "ambiance_recipe_id": "ambiance-2026-05-03-a-varied-saved-signal-field-selected-by-source-quality-rende-v2",
  "motion_system": "source-shaped drift",
  "color_drift": "balance luminous accents with grounded neutrals drawn from the research set",
  "glow_behavior": "artifact-proximity",
  "audio_posture": "silent",
  "webgl_mode": "none",
  "research_inputs": [
    "research-1-5edcb98a",
    "research-2-80976fa9",
    "research-3-736d010c",
    "research-4-4fe99639",
    "research-5-c4c0c715",
    "research-6-a8f1625d",
    "research-7-30310d9c",
    "research-8-5ce9b0bd",
    "research-9-027df24d",
    "research-10-ac352c5a",
    "research-11-82f59734",
    "research-12-692e7fc6"
  ]
}
