{
  "source_visual_metadata_id": "source-visuals-2026-07-10-pale-internet-herbarium-v1",
  "edition_id": "2026-07-10-pale-internet-herbarium-v1",
  "generated_by": "prepare-source-visuals/supervision",
  "records": [
    {
      "binding_id": "binding-hero-retro-index-hero-slip",
      "source_image_url": "https://pbs.twimg.com/media/HMJ7yzCXwAAYCWB.jpg?name=orig",
      "poster_asset_path": "/editions/2026-07-10-pale-internet-herbarium-v1/assets/source-posters/binding-hero-retro-index-hero-slip.jpg",
      "review_asset_path": "tmp/source-visual-qa/2026-07-10-pale-internet-herbarium-v1/binding-hero-retro-index-hero-slip-source-visual-qa.jpg",
      "image_width": 3014,
      "image_height": 1604,
      "aspect_ratio": 1.8791,
      "render_mode": "poster-crop",
      "crop_risk": "low",
      "focal_point": {
        "x": 0.4899,
        "y": 0.4726
      },
      "poster_crop": {
        "x": 0.0169,
        "y": 0.0,
        "width": 0.9459,
        "height": 1.0
      },
      "analysis": {
        "method": "supervision-contour-union",
        "supervision_version": "0.28.0",
        "edge_density": 0.01012,
        "candidate_box_count": 18
      }
    },
    {
      "binding_id": "binding-hero-living-itinerary-hero-island",
      "source_image_url": "https://pbs.twimg.com/amplify_video_thumb/2074233989120856064/img/FXOl29fSavwYTJKY.jpg",
      "poster_asset_path": "/editions/2026-07-10-pale-internet-herbarium-v1/assets/source-posters/binding-hero-living-itinerary-hero-island.jpg",
      "review_asset_path": "tmp/source-visual-qa/2026-07-10-pale-internet-herbarium-v1/binding-hero-living-itinerary-hero-island-source-visual-qa.jpg",
      "image_width": 1200,
      "image_height": 693,
      "aspect_ratio": 1.7316,
      "render_mode": "poster-crop",
      "crop_risk": "low",
      "focal_point": {
        "x": 0.5,
        "y": 0.4993
      },
      "poster_crop": {
        "x": 0.0,
        "y": 0.013,
        "width": 1.0,
        "height": 0.974
      },
      "analysis": {
        "method": "supervision-contour-union",
        "supervision_version": "0.28.0",
        "edge_density": 0.02228,
        "candidate_box_count": 16
      }
    },
    {
      "binding_id": "binding-module-typelit-book-page-cut",
      "source_image_url": "https://www.typelit.io/images/social-share-thumbnail.jpg",
      "poster_asset_path": "/editions/2026-07-10-pale-internet-herbarium-v1/assets/source-posters/binding-module-typelit-book-page-cut.jpg",
      "review_asset_path": "tmp/source-visual-qa/2026-07-10-pale-internet-herbarium-v1/binding-module-typelit-book-page-cut-source-visual-qa.jpg",
      "image_width": 1200,
      "image_height": 630,
      "aspect_ratio": 1.9048,
      "render_mode": "poster-crop",
      "crop_risk": "low",
      "focal_point": {
        "x": 0.3742,
        "y": 0.504
      },
      "poster_crop": {
        "x": 0.0,
        "y": 0.0,
        "width": 0.9333,
        "height": 1.0
      },
      "analysis": {
        "method": "supervision-contour-union",
        "supervision_version": "0.28.0",
        "edge_density": 0.06428,
        "candidate_box_count": 24
      }
    },
    {
      "binding_id": "binding-module-nityas-leisure-column",
      "source_image_url": "http://nityasnotes.com/images/when-we-cease-to-understand-the-world.jpg",
      "poster_asset_path": "/editions/2026-07-10-pale-internet-herbarium-v1/assets/source-posters/binding-module-nityas-leisure-column.jpg",
      "review_asset_path": "tmp/source-visual-qa/2026-07-10-pale-internet-herbarium-v1/binding-module-nityas-leisure-column-source-visual-qa.jpg",
      "image_width": 367,
      "image_height": 544,
      "aspect_ratio": 0.6746,
      "render_mode": "poster-crop",
      "crop_risk": "high",
      "focal_point": {
        "x": 0.5,
        "y": 0.5
      },
      "poster_crop": {
        "x": 0.0,
        "y": 0.3107,
        "width": 1.0,
        "height": 0.3787
      },
      "analysis": {
        "method": "supervision-contour-union",
        "supervision_version": "0.28.0",
        "edge_density": 0.16752,
        "candidate_box_count": 24
      }
    },
    {
      "binding_id": "binding-module-cod-recipe-glint",
      "source_image_url": "https://pbs.twimg.com/media/HMuUPXNXUAApxNF.jpg?name=orig",
      "poster_asset_path": "/editions/2026-07-10-pale-internet-herbarium-v1/assets/source-posters/binding-module-cod-recipe-glint.jpg",
      "review_asset_path": "tmp/source-visual-qa/2026-07-10-pale-internet-herbarium-v1/binding-module-cod-recipe-glint-source-visual-qa.jpg",
      "image_width": 1308,
      "image_height": 1176,
      "aspect_ratio": 1.1122,
      "render_mode": "poster-crop",
      "crop_risk": "medium",
      "focal_point": {
        "x": 0.3372,
        "y": 0.4494
      },
      "poster_crop": {
        "x": 0.0,
        "y": 0.1369,
        "width": 1.0,
        "height": 0.625
      },
      "analysis": {
        "method": "supervision-contour-union",
        "supervision_version": "0.28.0",
        "edge_density": 0.04759,
        "candidate_box_count": 4
      }
    },
    {
      "binding_id": "binding-module-anchor-image-orbit-chip",
      "source_image_url": "https://pbs.twimg.com/media/HMJ7yzCXwAAYCWB?format=webp&name=large",
      "poster_asset_path": "/editions/2026-07-10-pale-internet-herbarium-v1/assets/source-posters/binding-module-anchor-image-orbit-chip.jpg",
      "review_asset_path": "tmp/source-visual-qa/2026-07-10-pale-internet-herbarium-v1/binding-module-anchor-image-orbit-chip-source-visual-qa.jpg",
      "image_width": 2048,
      "image_height": 1090,
      "aspect_ratio": 1.8789,
      "render_mode": "poster-crop",
      "crop_risk": "low",
      "focal_point": {
        "x": 0.4905,
        "y": 0.4734
      },
      "poster_crop": {
        "x": 0.0176,
        "y": 0.0,
        "width": 0.9458,
        "height": 1.0
      },
      "analysis": {
        "method": "supervision-contour-union",
        "supervision_version": "0.28.0",
        "edge_density": 0.00994,
        "candidate_box_count": 19
      }
    },
    {
      "binding_id": "binding-module-midlife-square-repair",
      "source_image_url": "https://framerusercontent.com/images/HqoHkPp6dpJFdgMqUKIaAXmy7o.jpg?width=3220&height=3220",
      "poster_asset_path": "/editions/2026-07-10-pale-internet-herbarium-v1/assets/source-posters/binding-module-midlife-square-repair.jpg",
      "review_asset_path": "tmp/source-visual-qa/2026-07-10-pale-internet-herbarium-v1/binding-module-midlife-square-repair-source-visual-qa.jpg",
      "image_width": 3220,
      "image_height": 3220,
      "aspect_ratio": 1.0,
      "render_mode": "poster-crop",
      "crop_risk": "medium",
      "focal_point": {
        "x": 0.5604,
        "y": 0.516
      },
      "poster_crop": {
        "x": 0.0,
        "y": 0.2186,
        "width": 1.0,
        "height": 0.5624
      },
      "analysis": {
        "method": "supervision-contour-union",
        "supervision_version": "0.28.0",
        "edge_density": 0.09147,
        "candidate_box_count": 24
      }
    },
    {
      "binding_id": "binding-module-field-marker",
      "source_image_url": "https://pbs.twimg.com/media/HMJ7z3yWYAEneHZ?format=webp&name=large",
      "poster_asset_path": "/editions/2026-07-10-pale-internet-herbarium-v1/assets/source-posters/binding-module-field-marker.jpg",
      "review_asset_path": "tmp/source-visual-qa/2026-07-10-pale-internet-herbarium-v1/binding-module-field-marker-source-visual-qa.jpg",
      "image_width": 2048,
      "image_height": 1033,
      "aspect_ratio": 1.9826,
      "render_mode": "poster-crop",
      "crop_risk": "low",
      "focal_point": {
        "x": 0.5054,
        "y": 0.4898
      },
      "poster_crop": {
        "x": 0.0518,
        "y": 0.0,
        "width": 0.8965,
        "height": 1.0
      },
      "analysis": {
        "method": "supervision-contour-union",
        "supervision_version": "0.28.0",
        "edge_density": 0.03368,
        "candidate_box_count": 24
      }
    },
    {
      "binding_id": "binding-module-layered-fragment",
      "source_image_url": "https://framerusercontent.com/images/AX28DiXGE9IEUSTSdRTgQ5Cz2zE.png?width=184&height=186",
      "poster_asset_path": "/editions/2026-07-10-pale-internet-herbarium-v1/assets/source-posters/binding-module-layered-fragment.jpg",
      "review_asset_path": "tmp/source-visual-qa/2026-07-10-pale-internet-herbarium-v1/binding-module-layered-fragment-source-visual-qa.jpg",
      "image_width": 184,
      "image_height": 186,
      "aspect_ratio": 0.9892,
      "render_mode": "poster-crop",
      "crop_risk": "medium",
      "focal_point": {
        "x": 0.519,
        "y": 0.5188
      },
      "poster_crop": {
        "x": 0.0,
        "y": 0.2258,
        "width": 1.0,
        "height": 0.5538
      },
      "analysis": {
        "method": "supervision-contour-union",
        "supervision_version": "0.28.0",
        "edge_density": 0.03758,
        "candidate_box_count": 6
      }
    }
  ],
  "failures": []
}
