{
  "source_visual_metadata_id": "source-visuals-2026-06-16-isometric-window-section-v1",
  "edition_id": "2026-06-16-isometric-window-section-v1",
  "generated_by": "prepare-source-visuals/supervision",
  "records": [
    {
      "binding_id": "binding-hero-pixel-city-roof-cut",
      "source_image_url": "https://pbs.twimg.com/media/HKxq2VDWQAAluHu.jpg?name=orig",
      "poster_asset_path": "/editions/2026-06-16-isometric-window-section-v1/assets/source-posters/binding-hero-pixel-city-roof-cut.jpg",
      "review_asset_path": "tmp/source-visual-qa/2026-06-16-isometric-window-section-v1/binding-hero-pixel-city-roof-cut-source-visual-qa.jpg",
      "image_width": 1314,
      "image_height": 801,
      "aspect_ratio": 1.6404,
      "render_mode": "poster-crop",
      "crop_risk": "low",
      "focal_point": {
        "x": 0.5004,
        "y": 0.4981
      },
      "poster_crop": {
        "x": 0.0,
        "y": 0.0387,
        "width": 1.0,
        "height": 0.9226
      },
      "analysis": {
        "method": "supervision-contour-union",
        "supervision_version": "0.28.0",
        "edge_density": 0.14983,
        "candidate_box_count": 24
      }
    },
    {
      "binding_id": "binding-hero-multitudinous-window-bay",
      "source_image_url": "https://www.thisiscolossal.com/wp-content/uploads/2026/06/krugman-10-1536x864.jpeg",
      "poster_asset_path": "/editions/2026-06-16-isometric-window-section-v1/assets/source-posters/binding-hero-multitudinous-window-bay.jpg",
      "review_asset_path": "tmp/source-visual-qa/2026-06-16-isometric-window-section-v1/binding-hero-multitudinous-window-bay-source-visual-qa.jpg",
      "image_width": 1536,
      "image_height": 864,
      "aspect_ratio": 1.7778,
      "render_mode": "poster-crop",
      "crop_risk": "low",
      "focal_point": {
        "x": 0.5026,
        "y": 0.4988
      },
      "poster_crop": {
        "x": 0.0,
        "y": 0.0,
        "width": 1.0,
        "height": 1.0
      },
      "analysis": {
        "method": "supervision-contour-union",
        "supervision_version": "0.28.0",
        "edge_density": 0.03922,
        "candidate_box_count": 24
      }
    },
    {
      "binding_id": "binding-module-data-loom-map",
      "source_image_url": "https://pbs.twimg.com/amplify_video_thumb/2066113122436341760/img/RUam2qvynR0BRurT.jpg",
      "poster_asset_path": "/editions/2026-06-16-isometric-window-section-v1/assets/source-posters/binding-module-data-loom-map.jpg",
      "review_asset_path": "tmp/source-visual-qa/2026-06-16-isometric-window-section-v1/binding-module-data-loom-map-source-visual-qa.jpg",
      "image_width": 675,
      "image_height": 1200,
      "aspect_ratio": 0.5625,
      "render_mode": "poster-crop",
      "crop_risk": "high",
      "focal_point": {
        "x": 0.5644,
        "y": 0.5308
      },
      "poster_crop": {
        "x": 0.0,
        "y": 0.3733,
        "width": 1.0,
        "height": 0.3158
      },
      "analysis": {
        "method": "supervision-contour-union",
        "supervision_version": "0.28.0",
        "edge_density": 0.02103,
        "candidate_box_count": 24
      }
    },
    {
      "binding_id": "binding-module-serrated-stamp-ledge",
      "source_image_url": "https://marijanapav.com/stamps/opengraph-image.png?opengraph-image.01n96nd9h0awm.png",
      "poster_asset_path": "/editions/2026-06-16-isometric-window-section-v1/assets/source-posters/binding-module-serrated-stamp-ledge.jpg",
      "review_asset_path": "tmp/source-visual-qa/2026-06-16-isometric-window-section-v1/binding-module-serrated-stamp-ledge-source-visual-qa.jpg",
      "image_width": 1200,
      "image_height": 630,
      "aspect_ratio": 1.9048,
      "render_mode": "poster-crop",
      "crop_risk": "low",
      "focal_point": {
        "x": 0.47,
        "y": 0.4
      },
      "poster_crop": {
        "x": 0.0333,
        "y": 0.0,
        "width": 0.9333,
        "height": 1.0
      },
      "analysis": {
        "method": "supervision-contour-union",
        "supervision_version": "0.28.0",
        "edge_density": 0.03038,
        "candidate_box_count": 24
      }
    },
    {
      "binding_id": "binding-module-green-ridge-fissure",
      "source_image_url": "https://pbs.twimg.com/media/HKx03r_aoAAndME.jpg?name=orig",
      "poster_asset_path": "/editions/2026-06-16-isometric-window-section-v1/assets/source-posters/binding-module-green-ridge-fissure.jpg",
      "review_asset_path": "tmp/source-visual-qa/2026-06-16-isometric-window-section-v1/binding-module-green-ridge-fissure-source-visual-qa.jpg",
      "image_width": 2048,
      "image_height": 1638,
      "aspect_ratio": 1.2503,
      "render_mode": "poster-crop",
      "crop_risk": "low",
      "focal_point": {
        "x": 0.5215,
        "y": 0.3959
      },
      "poster_crop": {
        "x": 0.0,
        "y": 0.1154,
        "width": 1.0,
        "height": 0.7033
      },
      "analysis": {
        "method": "supervision-contour-union",
        "supervision_version": "0.28.0",
        "edge_density": 0.02576,
        "candidate_box_count": 24
      }
    },
    {
      "binding_id": "binding-module-body-landscape-glass-slit",
      "source_image_url": "https://www.thisiscolossal.com/wp-content/uploads/2026/06/dean-6-1536x1152.jpg",
      "poster_asset_path": "/editions/2026-06-16-isometric-window-section-v1/assets/source-posters/binding-module-body-landscape-glass-slit.jpg",
      "review_asset_path": "tmp/source-visual-qa/2026-06-16-isometric-window-section-v1/binding-module-body-landscape-glass-slit-source-visual-qa.jpg",
      "image_width": 1536,
      "image_height": 1152,
      "aspect_ratio": 1.3333,
      "render_mode": "poster-crop",
      "crop_risk": "low",
      "focal_point": {
        "x": 0.5,
        "y": 0.5503
      },
      "poster_crop": {
        "x": 0.0,
        "y": 0.125,
        "width": 1.0,
        "height": 0.75
      },
      "analysis": {
        "method": "supervision-contour-union",
        "supervision_version": "0.28.0",
        "edge_density": 0.08561,
        "candidate_box_count": 24
      }
    },
    {
      "binding_id": "binding-module-woodcut-memory-seam",
      "source_image_url": "https://www.thisiscolossal.com/wp-content/uploads/2026/06/gratovich-6-1170x2048.jpeg",
      "poster_asset_path": "/editions/2026-06-16-isometric-window-section-v1/assets/source-posters/binding-module-woodcut-memory-seam.jpg",
      "review_asset_path": "tmp/source-visual-qa/2026-06-16-isometric-window-section-v1/binding-module-woodcut-memory-seam-source-visual-qa.jpg",
      "image_width": 1170,
      "image_height": 2048,
      "aspect_ratio": 0.5713,
      "render_mode": "poster-crop",
      "crop_risk": "high",
      "focal_point": {
        "x": 0.5013,
        "y": 0.4937
      },
      "poster_crop": {
        "x": 0.0,
        "y": 0.3394,
        "width": 1.0,
        "height": 0.3213
      },
      "analysis": {
        "method": "supervision-contour-union",
        "supervision_version": "0.28.0",
        "edge_density": 0.13902,
        "candidate_box_count": 1
      }
    },
    {
      "binding_id": "binding-module-rich-message-amber-panel",
      "source_image_url": "https://i.ytimg.com/vi/nY1zltFn8xE/oar2.jpg?sqp=-oaymwEkCJUDENAFSFqQAgHyq4qpAxMIARUAAAAAJQAAyEI9AICiQ3gB&rs=AOn4CLBZv_sHFOVaBLph9LvDiVibanytYg&usqp=CCk",
      "poster_asset_path": "/editions/2026-06-16-isometric-window-section-v1/assets/source-posters/binding-module-rich-message-amber-panel.jpg",
      "review_asset_path": "tmp/source-visual-qa/2026-06-16-isometric-window-section-v1/binding-module-rich-message-amber-panel-source-visual-qa.jpg",
      "image_width": 405,
      "image_height": 720,
      "aspect_ratio": 0.5625,
      "render_mode": "poster-crop",
      "crop_risk": "high",
      "focal_point": {
        "x": 0.5,
        "y": 0.5
      },
      "poster_crop": {
        "x": 0.0,
        "y": 0.3417,
        "width": 1.0,
        "height": 0.3153
      },
      "analysis": {
        "method": "supervision-contour-union",
        "supervision_version": "0.28.0",
        "edge_density": 0.0582,
        "candidate_box_count": 24
      }
    },
    {
      "binding_id": "binding-module-rich-message-amber-panel-2",
      "source_image_url": "https://pbs.twimg.com/amplify_video_thumb/2066197749373014016/img/82qUW_oJKc5oaxUQ.jpg",
      "poster_asset_path": "/editions/2026-06-16-isometric-window-section-v1/assets/source-posters/binding-module-rich-message-amber-panel-2.jpg",
      "review_asset_path": "tmp/source-visual-qa/2026-06-16-isometric-window-section-v1/binding-module-rich-message-amber-panel-2-source-visual-qa.jpg",
      "image_width": 552,
      "image_height": 1199,
      "aspect_ratio": 0.4604,
      "render_mode": "poster-crop",
      "crop_risk": "high",
      "focal_point": {
        "x": 0.4982,
        "y": 0.4954
      },
      "poster_crop": {
        "x": 0.0,
        "y": 0.3703,
        "width": 1.0,
        "height": 0.2585
      },
      "analysis": {
        "method": "supervision-contour-union",
        "supervision_version": "0.28.0",
        "edge_density": 0.08894,
        "candidate_box_count": 24
      }
    }
  ],
  "failures": []
}
