{
  "ambiance_recipe_id": "ambiance-2026-07-16-glazed-edge-habitat-v1",
  "motion_system": "slow route-branching pressure under the surface, like a game map growing through wet paper",
  "color_drift": "warm paper neutrals and ceramic creams interrupted by blue-gray screen fragments, coral glints, and muted graphite",
  "glow_behavior": "localized specular glints pool around cuts and glossy media grains, never full-screen bloom",
  "audio_posture": "ambient",
  "webgl_mode": "shader-scene",
  "research_inputs": [
    "research-1-bc78b509",
    "research-2-d39d9729",
    "research-3-aee1cc52",
    "research-4-055cf7d4",
    "research-5-cf461952",
    "research-6-d86c1cf5",
    "research-7-45d92834",
    "research-8-a9031d38",
    "research-9-c97fa13e",
    "research-10-d0b432e3",
    "research-11-b37400d0",
    "research-12-fa49b2ef"
  ]
}
